[
	{
		"id":1,
		"question":"宋仲基说“刷我的卡”，指的是让宝宝刷哪张卡？",
		"options":[
			{"opt":"联名卡"},
			{"opt":"附属卡"},
			{"opt":"饭卡"}
		],
		"answer":"联名卡"
	},
	{
		"id":2,
		"question":"关于信用卡的说法，哪个正确？",
		"options":[
			{"opt":"使用信用卡一定要输入密码"},
			{"opt":"信用卡逾期不会影响征信记录"},
			{"opt":"信用卡积分可以当钱花"}
		],
		"answer":"信用卡积分可以当钱花"
	},
	{
		"id":3,
		"question":"BABY想吃50元的牛排，喝50块的拉菲，但晓明只有50元怎么办？",
		"options":[
			{"opt":"跟BABY分手"},
			{"opt":"让BABY多喝开水"},
			{"opt":"刷交行信用卡享受满100减50优惠"}
		],
		"answer":"刷交行信用卡享受满100减50优惠"
	},
	{
		"id":4,
		"question":"剁手族小月要办信用卡，哪一张适合他？",
		"options":[
			{"opt":"平安淘宝卡用积分当钱花"},
			{"opt":"光大阳光卡10元看大片"},
			{"opt":"广发携程卡享积分换里程"}
		],
		"answer":"平安淘宝卡用积分当钱花"
	},
	{
		"id":5,
		"question":"以下哪个渠道办理信用卡最方便可靠？",
		"options":[
			{"opt":"来路不明的办卡小广告"},
			{"opt":"极速办卡的银行合作方-随手记APP"},
			{"opt":"收取手续费的街边摊位"}
		],
		"answer":"极速办卡的银行合作方-随手记APP"
	},
	{
		"id":6,
		"list":[
			{"tit":"10元看大片","content":"使用中国光大银行信用卡在指定影院仅刷10元即可购得当天电影票一张"},
			{"tit":"其他优惠","content":"开卡首年送3万积分。首创自选免息分期功能"},
			{"tit":"年费信息","content":"首年免年费，当年消费3笔或累计金额2000元，免次年年费"}
		]
	}
]